aiosendspin_mpris/__init__.py
aiosendspin_mpris/adapter.py
aiosendspin_mpris/mpris.py
aiosendspin_mpris/mpris_service.py
aiosendspin_mpris-2.1.1.dist-info/licenses/LICENSE
aiosendspin_mpris-2.1.1.dist-info/METADATA
aiosendspin_mpris-2.1.1.dist-info/WHEEL
aiosendspin_mpris-2.1.1.dist-info/top_level.txt
aiosendspin_mpris-2.1.1.dist-info/RECORD
